tactus_live/__init__.py
tactus_live/main.py
tactus_live/utils/kafka_producer.py
tactus_live-1.2.0.dist-info/METADATA
tactus_live-1.2.0.dist-info/WHEEL
tactus_live-1.2.0.dist-info/top_level.txt
tactus_live-1.2.0.dist-info/RECORD
