Metadata-Version: 2.1
Name: tactus-live
Version: 1.2.0
Summary: Threatening activities classification toward users' security
Project-URL: repository, https://github.com/Cranfield-GDP3/TACTUS-live
Classifier: Development Status :: 5 - Production/Stable
Classifier: Intended Audience :: Developers
Classifier: Programming Language :: Python
Requires-Python: >=3.8
Requires-Dist: opencv-python
Requires-Dist: confluent-kafka
Requires-Dist: tactus-data (>=1.1.3)
Requires-Dist: tactus-model (>=1.0.0)
Requires-Dist: tactus-deep-sort-realtime
Requires-Dist: pytest
